setup.py
smartfeed/__init__.py
smartfeed.egg-info/PKG-INFO
smartfeed.egg-info/SOURCES.txt
smartfeed.egg-info/dependency_links.txt
smartfeed.egg-info/requires.txt
smartfeed.egg-info/top_level.txt
smartfeed/django/__init__.py
smartfeed/django/app/__init__.py
smartfeed/django/app/urls.py
smartfeed/django/app/views.py