Metadata-Version: 1.1
Name: smartfeed
Version: 1.0.0
Summary: Fanout Smart Feed
Home-page: https://github.com/fanout/pysmartfeed
Author: Justin Karneges
Author-email: justin@fanout.io
License: MIT
Platform: UNKNOWN
Classifier: Topic :: Utilities
Classifier: License :: OSI Approved :: MIT License
